tap_zohosprints/__init__.py
tap_zohosprints/client.py
tap_zohosprints/schemas/backlog.json
tap_zohosprints/schemas/epic.json
tap_zohosprints/schemas/item.json
tap_zohosprints/schemas/project.json
tap_zohosprints/schemas/project_user.json
tap_zohosprints/schemas/sprint.json
tap_zohosprints/schemas/sprint_user.json
tap_zohosprints/schemas/tag.json
tap_zohosprints/schemas/team.json
tap_zohosprints/streams.py
tap_zohosprints/tap.py
tap_zohosprints/tests/__init__.py
tap_zohosprints/tests/tag_property_unfurl.json
tap_zohosprints/tests/test_core.py
tap_zohosprints-0.0.5.dist-info/METADATA
tap_zohosprints-0.0.5.dist-info/WHEEL
tap_zohosprints-0.0.5.dist-info/entry_points.txt
tap_zohosprints-0.0.5.dist-info/RECORD
