Metadata-Version: 2.1
Name: tap-zohosprints
Version: 0.0.5
Summary: `tap-zohosprints` is a Singer tap for ZohoSprints, built with the Meltano SDK for Singer Taps.
License: Apache 2.0
Author: AutoIDM
Requires-Python: >=3.8.1
Classifier: License :: Other/Proprietary License
Classifier: Programming Language :: Python :: 3
Classifier: Programming Language :: Python :: 3.9
Classifier: Programming Language :: Python :: 3.10
Classifier: Programming Language :: Python :: 3.11
Classifier: Programming Language :: Python :: 3.12
Requires-Dist: requests (>=2.25.1,<3.0.0)
Requires-Dist: singer-sdk (==0.3.17)
